when/__init__.py
when/__main__.py
when/config.py
when/data/cities.json
when/model.py
when/rich_typer.py
when/when.py
when_cli-1.1.2.dist-info/entry_points.txt
when_cli-1.1.2.dist-info/WHEEL
when_cli-1.1.2.dist-info/METADATA
when_cli-1.1.2.dist-info/RECORD
